bsb/__init__.py
bsb/__main__.py
bsb/_contexts.py
bsb/_encoding.py
bsb/_options.py
bsb/_package_spec.py
bsb/_util.py
bsb/cell_types.py
bsb/core.py
bsb/exceptions.py
bsb/mixins.py
bsb/option.py
bsb/options.py
bsb/plugins.py
bsb/postprocessing.py
bsb/profiling.py
bsb/reporting.py
bsb/trees.py
bsb/voxels.py
bsb/cli/__init__.py
bsb/cli/commands/__init__.py
bsb/cli/commands/_commands.py
bsb/cli/commands/_projects.py
bsb/config/__init__.py
bsb/config/_attrs.py
bsb/config/_compile.py
bsb/config/_config.py
bsb/config/_distributions.py
bsb/config/_hooks.py
bsb/config/_make.py
bsb/config/_parse_types.py
bsb/config/parsers.py
bsb/config/refs.py
bsb/config/types.py
bsb/connectivity/__init__.py
bsb/connectivity/general.py
bsb/connectivity/import_.py
bsb/connectivity/strategy.py
bsb/connectivity/detailed/__init__.py
bsb/connectivity/detailed/shared.py
bsb/connectivity/detailed/voxel_intersection.py
bsb/connectivity/geometric/__init__.py
bsb/connectivity/geometric/geometric_shapes.py
bsb/connectivity/geometric/morphology_shape_intersection.py
bsb/connectivity/geometric/shape_morphology_intersection.py
bsb/connectivity/geometric/shape_shape_intersection.py
bsb/morphologies/__init__.py
bsb/morphologies/selector.py
bsb/morphologies/parsers/__init__.py
bsb/morphologies/parsers/parser.py
bsb/placement/__init__.py
bsb/placement/arrays.py
bsb/placement/distributor.py
bsb/placement/import_.py
bsb/placement/indicator.py
bsb/placement/random.py
bsb/placement/strategy.py
bsb/services/__init__.py
bsb/services/_pool_listeners.py
bsb/services/_util.py
bsb/services/mpi.py
bsb/services/mpilock.py
bsb/services/pool.py
bsb/simulation/__init__.py
bsb/simulation/_backends.py
bsb/simulation/adapter.py
bsb/simulation/cell.py
bsb/simulation/component.py
bsb/simulation/connection.py
bsb/simulation/device.py
bsb/simulation/parameter.py
bsb/simulation/results.py
bsb/simulation/simulation.py
bsb/simulation/targetting.py
bsb/storage/__init__.py
bsb/storage/_chunks.py
bsb/storage/_files.py
bsb_core-7.2.1.dist-info/entry_points.txt
bsb_core-7.2.1.dist-info/licenses/LICENSE
bsb_core-7.2.1.dist-info/WHEEL
bsb_core-7.2.1.dist-info/METADATA
bsb_core-7.2.1.dist-info/RECORD
