Metadata-Version: 2.4
Name: bsb-core
Version: 7.2.1
Summary: `bsb-core` is the backbone package contain the essential code of the BSB: A component
Author-email: Robin De Schepper <robin@alexandria.sc>, Dimitri Rodarie <dimitri.rodarie@unipv.it>
Requires-Python: >=3.10,<4
Classifier: License :: OSI Approved :: GNU General Public License v3 or later (GPLv3+)
License-File: LICENSE
Requires-Dist: numpy~=1.19
Requires-Dist: scipy~=1.5
Requires-Dist: scikit-learn~=1.0
Requires-Dist: errr~=1.2
Requires-Dist: rtree~=1.0
Requires-Dist: psutil~=5.8
Requires-Dist: voxcell~=3.1
Requires-Dist: morphio~=3.3
Requires-Dist: toml~=0.10.0
Requires-Dist: requests~=2.30
Requires-Dist: urllib3~=2.0
Requires-Dist: appdirs~=1.4
Requires-Dist: neo[nixio]~=0.13
Requires-Dist: tqdm~=4.50
Requires-Dist: dashing-next~=0.1
Requires-Dist: shortuuid~=1.0
Requires-Dist: quantities~=0.15.0
Requires-Dist: exceptiongroup>=1.2.0
Requires-Dist: opentelemetry-api~=1.0
Requires-Dist: mpi4py~=3.0 ; extra == "parallel"
Requires-Dist: mpipool>=2.2.1,<3 ; extra == "parallel"
Requires-Dist: mpilock~=1.1 ; extra == "parallel"
Provides-Extra: parallel
